report_generation/__init__.py
report_generation/report.py
report_generation-0.0.1.dist-info/METADATA
report_generation-0.0.1.dist-info/WHEEL
report_generation-0.0.1.dist-info/top_level.txt
report_generation-0.0.1.dist-info/RECORD
