Metadata-Version: 2.1
Name: report-generation
Version: 0.0.1
Summary: report generation Package
Home-page: UNKNOWN
Author: Athira
Author-email: athiraparnnasala@gmail.com
License: UNKNOWN
Platform: UNKNOWN
